Workbook

Sheet Summary
A1: NEXORA – Measure Dictionary Summary
A2: Counts recalculate from the Measures sheet.
A4: Total measures | B4: =COUNTA(Measures!$D$5:$D$214) -> 210
A5: Measures with a reference value | B5: =COUNT(Measures!$K$5:$K$214) -> 46
A7: Folder | B7: Measures | D7: Data type | E7: Measures
A8: 00 Utilities | B8: =COUNTIF(Measures!$B$5:$B$214,A8) -> 5 | D8: Currency | E8: =COUNTIF(Measures!$H$5:$H$214,D8) -> 43
A9: 01 Sales & Profit | B9: =COUNTIF(Measures!$B$5:$B$214,A9) -> 32 | D9: Whole number | E9: =COUNTIF(Measures!$H$5:$H$214,D9) -> 42
A10: 02 Time Intelligence | B10: =COUNTIF(Measures!$B$5:$B$214,A10) -> 26 | D10: Decimal | E10: =COUNTIF(Measures!$H$5:$H$214,D10) -> 11
A11: 03 KPI Cards | B11: =COUNTIF(Measures!$B$5:$B$214,A11) -> 15 | D11: Percentage | E11: =COUNTIF(Measures!$H$5:$H$214,D11) -> 60
A12: 04 Products & Brands | B12: =COUNTIF(Measures!$B$5:$B$214,A12) -> 33 | D12: Ratio | E12: =COUNTIF(Measures!$H$5:$H$214,D12) -> 1
A13: 05 Customers | B13: =COUNTIF(Measures!$B$5:$B$214,A13) -> 25 | D13: Date | E13: =COUNTIF(Measures!$H$5:$H$214,D13) -> 2
A14: 06 Marketing & Channels | B14: =COUNTIF(Measures!$B$5:$B$214,A14) -> 12 | D14: Text | E14: =COUNTIF(Measures!$H$5:$H$214,D14) -> 38
A15: 07 Operations | B15: =COUNTIF(Measures!$B$5:$B$214,A15) -> 15 | D15: Color (hex) | E15: =COUNTIF(Measures!$H$5:$H$214,D15) -> 13
A16: 08 Customer Experience | B16: =COUNTIF(Measures!$B$5:$B$214,A16) -> 10 | D16: Total | E16: =SUM(E8:E15) -> 210
A17: 09 Insights & Titles | B17: =COUNTIF(Measures!$B$5:$B$214,A17) -> 27
A18: 10 Data Quality | B18: =COUNTIF(Measures!$B$5:$B$214,A18) -> 10
A19: Total | B19: =SUM(B8:B18) -> 210
A20: Check (should equal Total measures) | B20: =IF(B19=B4,"OK","MISMATCH") -> OK
A22: Delivered TMDL scripts
A23: Script file | B23: Measures
A24: NEXORA_Customers_Page_Addon.tmdl.txt | B24: =COUNTIF(Measures!$L$5:$L$214,A24) -> 5
A25: NEXORA_Decision_Page_Addon.tmdl.txt | B25: =COUNTIF(Measures!$L$5:$L$214,A25) -> 17
A26: NEXORA_Measures_Core.tmdl.txt | B26: =COUNTIF(Measures!$L$5:$L$214,A26) -> 170
A27: NEXORA_Product_Performance.tmdl.txt | B27: =COUNTIF(Measures!$L$5:$L$214,A27) -> 2
A28: NEXORA_Products_Page_Addon.tmdl.txt | B28: =COUNTIF(Measures!$L$5:$L$214,A28) -> 15
A29: chat (single measure) | B29: =COUNTIF(Measures!$L$5:$L$214,A29) -> 1
A31: How to use: open the Measures sheet, filter by Folder or search a measure name; the DAX formula column can be copied as-is.
A32: Measures you created yourself in Power BI (for example the KPI visuals' own deltas) are not part of this list.
A33: Folder names match the Display folders in Power BI's Data pane, so the dictionary mirrors the model.

Sheet Measures
A1: NEXORA – DAX Measure Dictionary
A2: Every measure delivered in the TMDL scripts, grouped by display folder. Use the filter arrows on row 4.
A4: # | B4: Folder | C4: Subfolder | D4: Measure | E4: Description | F4: DAX formula | G4: Format string | H4: Data type | I4: Source tables | J4: Depends on | K4: Reference value (Year = 2025) | L4: Script file
A5: 1 | B5: 00 Utilities | D5: Data Through Date | E5: Latest order date in the data, ignoring all filters. | F5: CALCULATE(MAX(Orders[order_date]), REMOVEFILTERS()) | G5: dd-mmm-yyyy | H5: Date | I5: Orders | L5: NEXORA_Measures_Core.tmdl.txt
A6: 2 | B6: 00 Utilities | D6: Data Through Label | E6: Footer text for the report. | F6: "Data through " & FORMAT([Data Through Date], "dd mmm yyyy") | G6: (text) | H6: Text | J6: Data Through Date | L6: NEXORA_Measures_Core.tmdl.txt
A7: 3 | B7: 00 Utilities | D7: Selected Year | E7: Shows the selected year or All Years. | F7: IF(HASONEVALUE('Calendar'[Year]), FORMAT(SELECTEDVALUE('Calendar'[Year]), "0"), "All Years") | G7: (text) | H7: Text | I7: Calendar | L7: NEXORA_Measures_Core.tmdl.txt
A8: 4 | B8: 00 Utilities | D8: Period Label | E8: Subtitle describing the selected period. | F8: IF(HASONEVALUE('Calendar'[Year]), "Year " & FORMAT(SELECTEDVALUE('Calendar'[Year]), "0"), FORMAT(MIN('Calendar'[Date]), "MMM yyyy") & " – " & FORMAT(MAX('Calendar'[Date]), "MMM yyyy")) | G8: (text) | H8: Text | I8: Calendar | L8: NEXORA_Measures_Core.tmdl.txt
A9: 5 | B9: 00 Utilities | D9: Active Days | E9: Number of days with at least one valid order. | F9: CALCULATE( DISTINCTCOUNT(Orders[order_date]), Orders[order_status] <> "Cancelled", Orders[delivery_status] <> "Cancelled" ) | G9: #,0 | H9: Whole number | I9: Orders | L9: NEXORA_Measures_Core.tmdl.txt
A10: 6 | B10: 01 Sales & Profit | C10: Basket & Averages | D10: AOV | E10: Average order value. | F10: DIVIDE([Net Sales], [Total Orders]) | G10: \$#,0.00 | H10: Currency | J10: Net Sales, Total Orders | K10: 463.52 | L10: NEXORA_Measures_Core.tmdl.txt
A11: 7 | B11: 01 Sales & Profit | C11: Basket & Averages | D11: Units per Order | E11: Average number of units in a valid order. | F11: DIVIDE([Units Sold], [Total Orders]) | G11: 0.00 | H11: Decimal | J11: Units Sold, Total Orders | L11: NEXORA_Measures_Core.tmdl.txt
A12: 8 | B12: 01 Sales & Profit | C12: Basket & Averages | D12: Profit per Order | E12: Average profit earned per valid order. | F12: DIVIDE([Total Profit], [Total Orders]) | G12: \$#,0.00 | H12: Currency | J12: Total Profit, Total Orders | L12: NEXORA_Measures_Core.tmdl.txt
A13: 9 | B13: 01 Sales & Profit | C13: Basket & Averages | D13: Avg Selling Price | E13: Average gross selling price per unit sold. | F13: DIVIDE([Gross Sales], [Units Sold]) | G13: \$#,0.00 | H13: Currency | J13: Gross Sales, Units Sold | L13: NEXORA_Measures_Core.tmdl.txt
A14: 10 | B14: 01 Sales & Profit | C14: Basket & Averages | D14: Profit per Unit | E14: Average profit earned per unit sold. | F14: DIVIDE([Total Profit], [Units Sold]) | G14: \$#,0.00 | H14: Currency | J14: Total Profit, Units Sold | L14: NEXORA_Measures_Core.tmdl.txt
A15: 11 | B15: 01 Sales & Profit | C15: Core KPIs | D15: Gross Sales | E15: Quantity x unit price before discounts, tax and shipping. Cancelled orders excluded. | F15: CALCULATE( SUM(OrderItems[gross_sales]), Orders[order_status] <> "Cancelled", Orders[delivery_status] <> "Cancelled" ) | G15: \$#,0 | H15: Currency | I15: OrderItems, Orders | L15: NEXORA_Measures_Core.tmdl.txt
A16: 12 | B16: 01 Sales & Profit | C16: Core KPIs | D16: Discount | E16: Total discount value given. | F16: CALCULATE( SUM(OrderItems[discount_amount]), Orders[order_status] <> "Cancelled", Orders[delivery_status] <> "Cancelled" ) | G16: \$#,0 | H16: Currency | I16: OrderItems, Orders | L16: NEXORA_Measures_Core.tmdl.txt
A17: 13 | B17: 01 Sales & Profit | C17: Core KPIs | D17: Tax | E17: Tax charged on valid orders. | F17: CALCULATE( SUM(OrderItems[tax_amount]), Orders[order_status] <> "Cancelled", Orders[delivery_status] <> "Cancelled" ) | G17: \$#,0 | H17: Currency | I17: OrderItems, Orders | L17: NEXORA_Measures_Core.tmdl.txt
A18: 14 | B18: 01 Sales & Profit | C18: Core KPIs | D18: Shipping Cost | E18: Shipping cost charged on valid orders. | F18: CALCULATE( SUM(OrderItems[shipping_cost]), Orders[order_status] <> "Cancelled", Orders[delivery_status] <> "Cancelled" ) | G18: \$#,0 | H18: Currency | I18: OrderItems, Orders | L18: NEXORA_Measures_Core.tmdl.txt
A19: 15 | B19: 01 Sales & Profit | C19: Core KPIs | D19: Net Sales | E19: Gross - discount + tax + shipping (dataset definition). Cancelled orders excluded. | F19: CALCULATE( SUM(OrderItems[net_sales]), Orders[order_status] <> "Cancelled", Orders[delivery_status] <> "Cancelled" ) | G19: \$#,0 | H19: Currency | I19: OrderItems, Orders | K19: 5654533 | L19: NEXORA_Measures_Core.tmdl.txt
A20: 16 | B20: 01 Sales & Profit | C20: Core KPIs | D20: Product Cost | E20: Cost of the goods sold on valid orders. | F20: CALCULATE( SUM(OrderItems[product_cost]), Orders[order_status] <> "Cancelled", Orders[delivery_status] <> "Cancelled" ) | G20: \$#,0 | H20: Currency | I20: OrderItems, Orders | L20: NEXORA_Measures_Core.tmdl.txt
A21: 17 | B21: 01 Sales & Profit | C21: Core KPIs | D21: Total Profit | E21: Net sales - product cost - shipping cost (dataset definition). | F21: CALCULATE( SUM(OrderItems[profit]), Orders[order_status] <> "Cancelled", Orders[delivery_status] <> "Cancelled" ) | G21: \$#,0 | H21: Currency | I21: OrderItems, Orders | K21: 1910697 | L21: NEXORA_Measures_Core.tmdl.txt
A22: 18 | B22: 01 Sales & Profit | C22: Core KPIs | D22: Units Sold | E22: Total quantity sold on valid orders. | F22: CALCULATE( SUM(OrderItems[quantity]), Orders[order_status] <> "Cancelled", Orders[delivery_status] <> "Cancelled" ) | G22: #,0 | H22: Whole number | I22: OrderItems, Orders | K22: 54436 | L22: NEXORA_Measures_Core.tmdl.txt
A23: 19 | B23: 01 Sales & Profit | C23: Core KPIs | D23: Total Orders | E23: Distinct valid orders (cancelled excluded). | F23: CALCULATE( DISTINCTCOUNT(OrderItems[order_id]), Orders[order_status] <> "Cancelled", Orders[delivery_status] <> "Cancelled" ) | G23: #,0 | H23: Whole number | I23: OrderItems, Orders | K23: 12199 | L23: NEXORA_Measures_Core.tmdl.txt
A24: 20 | B24: 01 Sales & Profit | C24: Core KPIs | D24: Order Lines | E24: Number of order line items. | F24: CALCULATE( COUNTROWS(OrderItems), Orders[order_status] <> "Cancelled", Orders[delivery_status] <> "Cancelled" ) | G24: #,0 | H24: Whole number | I24: Orders | L24: NEXORA_Measures_Core.tmdl.txt
A25: 21 | B25: 01 Sales & Profit | C25: Core KPIs | D25: Net Revenue | E25: Gross sales minus discounts (excludes tax and shipping). | F25: [Gross Sales] - [Discount] | G25: \$#,0 | H25: Currency | J25: Gross Sales, Discount | L25: NEXORA_Measures_Core.tmdl.txt
A26: 22 | B26: 01 Sales & Profit | C26: Core KPIs | D26: Merchandise Profit | E26: Product profit before tax and shipping effects. | F26: [Net Revenue] - [Product Cost] | G26: \$#,0 | H26: Currency | J26: Net Revenue, Product Cost | L26: NEXORA_Measures_Core.tmdl.txt
A27: 23 | B27: 01 Sales & Profit | C27: Core KPIs | D27: Profit Margin % | E27: Total profit / net sales (same definition as the dataset). | F27: DIVIDE([Total Profit], [Net Sales]) | G27: 0.0% | H27: Percentage | J27: Total Profit, Net Sales | K27: 0.3379 | L27: NEXORA_Measures_Core.tmdl.txt
A28: 24 | B28: 01 Sales & Profit | C28: Core KPIs | D28: Merchandise Margin % | E28: Product margin on net revenue, before tax and shipping. | F28: DIVIDE([Merchandise Profit], [Net Revenue]) | G28: 0.0% | H28: Percentage | J28: Merchandise Profit, Net Revenue | K28: 0.258 | L28: NEXORA_Measures_Core.tmdl.txt
A29: 25 | B29: 01 Sales & Profit | C29: Discounts | D29: Discount % | E29: Discount value as % of gross sales. | F29: DIVIDE([Discount], [Gross Sales]) | G29: 0.0% | H29: Percentage | J29: Discount, Gross Sales | K29: 0.15 | L29: NEXORA_Measures_Core.tmdl.txt
A30: 26 | B30: 01 Sales & Profit | C30: Discounts | D30: Avg Line Discount % | E30: Simple average of the discount percentage across order lines. | F30: CALCULATE( AVERAGE(OrderItems[discount_percentage]), Orders[order_status] <> "Cancelled", Orders[delivery_status] <> "Cancelled" ) | G30: 0.0% | H30: Percentage | I30: OrderItems, Orders | L30: NEXORA_Measures_Core.tmdl.txt
A31: 27 | B31: 01 Sales & Profit | C31: Discounts | D31: High Discount Sales Share % | E31: Share of net sales on lines discounted 30% or more. | F31: DIVIDE(CALCULATE([Net Sales], OrderItems[discount_percentage] >= 0.3), [Net Sales]) | G31: 0.0% | H31: Percentage | I31: OrderItems | J31: Net Sales | K31: 0.075 | L31: NEXORA_Measures_Core.tmdl.txt
A32: 28 | B32: 01 Sales & Profit | C32: Discounts | D32: Margin % (Discount >= 30%) | E32: Profit margin on lines discounted 30% or more. | F32: DIVIDE(CALCULATE([Total Profit], OrderItems[discount_percentage] >= 0.3), CALCULATE([Net Sales], OrderItems[discount_percentage] >= 0.3)) | G32: 0.0% | H32: Percentage | I32: OrderItems | J32: Total Profit, Net Sales | K32: 0.116 | L32: NEXORA_Measures_Core.tmdl.txt
A33: 29 | B33: 01 Sales & Profit | C33: Discounts | D33: Margin % (Discount < 10%) | E33: Profit margin on lines discounted less than 10%. | F33: DIVIDE(CALCULATE([Total Profit], OrderItems[discount_percentage] < 0.1), CALCULATE([Net Sales], OrderItems[discount_percentage] < 0.1)) | G33: 0.0% | H33: Percentage | I33: OrderItems | J33: Total Profit, Net Sales | K33: 0.425 | L33: NEXORA_Measures_Core.tmdl.txt
A34: 30 | B34: 01 Sales & Profit | C34: Discounts | D34: Margin Erosion from Discounts (pts) | E34: Margin points lost on heavily discounted lines. | F34: [Margin % (Discount < 10%)] - [Margin % (Discount >= 30%)] | G34: 0.0% | H34: Percentage | J34: Margin % (Discount < 10%), Margin % (Discount >= 30%) | L34: NEXORA_Measures_Core.tmdl.txt
A35: 31 | B35: 01 Sales & Profit | C35: Order Status | D35: Net Sales (All Orders) | E35: Net sales including cancelled orders. | F35: SUM(OrderItems[net_sales]) | G35: \$#,0 | H35: Currency | I35: OrderItems | L35: NEXORA_Measures_Core.tmdl.txt
A36: 32 | B36: 01 Sales & Profit | C36: Order Status | D36: Orders (All Status) | E36: All orders including cancelled. | F36: DISTINCTCOUNT(OrderItems[order_id]) | G36: #,0 | H36: Whole number | I36: OrderItems | L36: NEXORA_Measures_Core.tmdl.txt
A37: 33 | B37: 01 Sales & Profit | C37: Order Status | D37: Cancelled Orders | E37: Orders lost to cancellation: all orders minus valid orders. | F37: [Orders (All Status)] - [Total Orders] | G37: #,0 | H37: Whole number | J37: Orders (All Status), Total Orders | L37: NEXORA_Measures_Core.tmdl.txt
A38: 34 | B38: 01 Sales & Profit | C38: Order Status | D38: Cancelled Sales | E38: Net sales value of cancelled orders: all-orders net sales minus valid net sales. | F38: [Net Sales (All Orders)] - [Net Sales] | G38: \$#,0 | H38: Currency | J38: Net Sales (All Orders), Net Sales | L38: NEXORA_Measures_Core.tmdl.txt
A39: 35 | B39: 01 Sales & Profit | C39: Order Status | D39: Cancellation Rate % | E39: Cancelled orders as a share of all orders. | F39: DIVIDE([Cancelled Orders], [Orders (All Status)]) | G39: 0.0% | H39: Percentage | J39: Cancelled Orders, Orders (All Status) | L39: NEXORA_Measures_Core.tmdl.txt
A40: 36 | B40: 01 Sales & Profit | C40: Order Status | D40: Completed Orders | E40: Orders whose status is Completed. | F40: CALCULATE(DISTINCTCOUNT(Orders[order_id]), Orders[order_status] = "Completed") | G40: #,0 | H40: Whole number | I40: Orders | L40: NEXORA_Measures_Core.tmdl.txt
A41: 37 | B41: 01 Sales & Profit | C41: Order Status | D41: Pending Orders | E41: Orders whose status is Pending. | F41: CALCULATE(DISTINCTCOUNT(Orders[order_id]), Orders[order_status] = "Pending") | G41: #,0 | H41: Whole number | I41: Orders | L41: NEXORA_Measures_Core.tmdl.txt
A42: 38 | B42: 02 Time Intelligence | C42: Month over Month | D42: Net Sales PM | E42: Net Sales in the previous month. | F42: CALCULATE([Net Sales], DATEADD('Calendar'[Date], -1, MONTH)) | G42: \$#,0 | H42: Currency | I42: Calendar | J42: Net Sales | L42: NEXORA_Measures_Core.tmdl.txt
A43: 39 | B43: 02 Time Intelligence | C43: Month over Month | D43: Net Sales MoM % | E43: Month-over-month growth of Net Sales. | F43: DIVIDE([Net Sales] - [Net Sales PM], [Net Sales PM]) | G43: 0.0% | H43: Percentage | J43: Net Sales, Net Sales PM | L43: NEXORA_Measures_Core.tmdl.txt
A44: 40 | B44: 02 Time Intelligence | C44: Month over Month | D44: Profit PM | E44: Profit in the previous month. | F44: CALCULATE([Total Profit], DATEADD('Calendar'[Date], -1, MONTH)) | G44: \$#,0 | H44: Currency | I44: Calendar | J44: Total Profit | L44: NEXORA_Measures_Core.tmdl.txt
A45: 41 | B45: 02 Time Intelligence | C45: Month over Month | D45: Profit MoM % | E45: Month-over-month growth of Profit. | F45: DIVIDE([Total Profit] - [Profit PM], [Profit PM]) | G45: 0.0% | H45: Percentage | J45: Total Profit, Profit PM | L45: NEXORA_Measures_Core.tmdl.txt
A46: 42 | B46: 02 Time Intelligence | C46: Month over Month | D46: Orders PM | E46: Orders in the previous month. | F46: CALCULATE([Total Orders], DATEADD('Calendar'[Date], -1, MONTH)) | G46: #,0 | H46: Whole number | I46: Calendar | J46: Total Orders | L46: NEXORA_Measures_Core.tmdl.txt
A47: 43 | B47: 02 Time Intelligence | C47: Month over Month | D47: Orders MoM % | E47: Month-over-month growth of Orders. | F47: DIVIDE([Total Orders] - [Orders PM], [Orders PM]) | G47: 0.0% | H47: Percentage | J47: Total Orders, Orders PM | L47: NEXORA_Measures_Core.tmdl.txt
A48: 44 | B48: 02 Time Intelligence | C48: Rolling Windows | D48: Net Sales 3M Rolling | E48: Net sales over the three months ending at the last date in the selection. | F48: CALCULATE([Net Sales], DATESINPERIOD('Calendar'[Date], MAX('Calendar'[Date]), -3, MONTH)) | G48: \$#,0 | H48: Currency | I48: Calendar | J48: Net Sales | L48: NEXORA_Measures_Core.tmdl.txt
A49: 45 | B49: 02 Time Intelligence | C49: Rolling Windows | D49: Net Sales TTM | E49: Trailing twelve months net sales. | F49: CALCULATE([Net Sales], DATESINPERIOD('Calendar'[Date], MAX('Calendar'[Date]), -12, MONTH)) | G49: \$#,0 | H49: Currency | I49: Calendar | J49: Net Sales | L49: NEXORA_Measures_Core.tmdl.txt
A50: 46 | B50: 02 Time Intelligence | C50: Rolling Windows | D50: Avg Daily Net Sales | E50: Net sales divided by the number of days that had at least one valid order. | F50: DIVIDE([Net Sales], [Active Days]) | G50: \$#,0.00 | H50: Currency | J50: Net Sales, Active Days | L50: NEXORA_Measures_Core.tmdl.txt
A51: 47 | B51: 02 Time Intelligence | C51: Rolling Windows | D51: Share of Year % | E51: Each period's share of its year (use with Month on the axis). | F51: DIVIDE([Net Sales], CALCULATE([Net Sales], ALLEXCEPT('Calendar', 'Calendar'[Year]))) | G51: 0.0% | H51: Percentage | I51: Calendar | J51: Net Sales | L51: NEXORA_Measures_Core.tmdl.txt
A52: 48 | B52: 02 Time Intelligence | C52: Running Totals | D52: Net Sales YTD | E52: Net sales accumulated from January 1 of the selected year up to the selected date. | F52: CALCULATE([Net Sales], DATESYTD('Calendar'[Date])) | G52: \$#,0 | H52: Currency | I52: Calendar | J52: Net Sales | L52: NEXORA_Measures_Core.tmdl.txt
A53: 49 | B53: 02 Time Intelligence | C53: Running Totals | D53: Profit YTD | E53: Profit accumulated from January 1 up to the selected date. | F53: CALCULATE([Total Profit], DATESYTD('Calendar'[Date])) | G53: \$#,0 | H53: Currency | I53: Calendar | J53: Total Profit | L53: NEXORA_Measures_Core.tmdl.txt
A54: 50 | B54: 02 Time Intelligence | C54: Running Totals | D54: Net Sales LYTD | E54: Year-to-date net sales for the same period last year. | F54: CALCULATE([Net Sales], DATESYTD(SAMEPERIODLASTYEAR('Calendar'[Date]))) | G54: \$#,0 | H54: Currency | I54: Calendar | J54: Net Sales | L54: NEXORA_Measures_Core.tmdl.txt
A55: 51 | B55: 02 Time Intelligence | C55: Running Totals | D55: YTD vs LYTD % | E55: Growth of year-to-date net sales against last year's year-to-date. | F55: DIVIDE([Net Sales YTD] - [Net Sales LYTD], [Net Sales LYTD]) | G55: 0.0% | H55: Percentage | J55: Net Sales YTD, Net Sales LYTD | L55: NEXORA_Measures_Core.tmdl.txt
A56: 52 | B56: 02 Time Intelligence | C56: Year over Year | D56: Net Sales LY | E56: Net Sales for the same period last year. | F56: CALCULATE([Net Sales], SAMEPERIODLASTYEAR('Calendar'[Date])) | G56: \$#,0 | H56: Currency | I56: Calendar | J56: Net Sales | L56: NEXORA_Measures_Core.tmdl.txt
A57: 53 | B57: 02 Time Intelligence | C57: Year over Year | D57: Net Sales YoY % | E57: Year-over-year growth of Net Sales versus the same period last year. | F57: DIVIDE([Net Sales] - [Net Sales LY], [Net Sales LY]) | G57: 0.0% | H57: Percentage | J57: Net Sales, Net Sales LY | K57: 0.2898 | L57: NEXORA_Measures_Core.tmdl.txt
A58: 54 | B58: 02 Time Intelligence | C58: Year over Year | D58: Profit LY | E58: Profit for the same period last year. | F58: CALCULATE([Total Profit], SAMEPERIODLASTYEAR('Calendar'[Date])) | G58: \$#,0 | H58: Currency | I58: Calendar | J58: Total Profit | L58: NEXORA_Measures_Core.tmdl.txt
A59: 55 | B59: 02 Time Intelligence | C59: Year over Year | D59: Profit YoY % | E59: Year-over-year growth of Profit versus the same period last year. | F59: DIVIDE([Total Profit] - [Profit LY], [Profit LY]) | G59: 0.0% | H59: Percentage | J59: Total Profit, Profit LY | K59: 0.2989 | L59: NEXORA_Measures_Core.tmdl.txt
A60: 56 | B60: 02 Time Intelligence | C60: Year over Year | D60: Orders LY | E60: Orders for the same period last year. | F60: CALCULATE([Total Orders], SAMEPERIODLASTYEAR('Calendar'[Date])) | G60: #,0 | H60: Whole number | I60: Calendar | J60: Total Orders | L60: NEXORA_Measures_Core.tmdl.txt
A61: 57 | B61: 02 Time Intelligence | C61: Year over Year | D61: Orders YoY % | E61: Year-over-year growth of Orders versus the same period last year. | F61: DIVIDE([Total Orders] - [Orders LY], [Orders LY]) | G61: 0.0% | H61: Percentage | J61: Total Orders, Orders LY | K61: 0.2991 | L61: NEXORA_Measures_Core.tmdl.txt
A62: 58 | B62: 02 Time Intelligence | C62: Year over Year | D62: AOV LY | E62: AOV for the same period last year. | F62: CALCULATE([AOV], SAMEPERIODLASTYEAR('Calendar'[Date])) | G62: \$#,0.00 | H62: Currency | I62: Calendar | J62: AOV | L62: NEXORA_Measures_Core.tmdl.txt
A63: 59 | B63: 02 Time Intelligence | C63: Year over Year | D63: AOV YoY % | E63: Year-over-year growth of AOV versus the same period last year. | F63: DIVIDE([AOV] - [AOV LY], [AOV LY]) | G63: 0.0% | H63: Percentage | J63: AOV, AOV LY | K63: -0.0072 | L63: NEXORA_Measures_Core.tmdl.txt
A64: 60 | B64: 02 Time Intelligence | C64: Year over Year | D64: Customers LY | E64: Customers for the same period last year. | F64: CALCULATE([Active Customers], SAMEPERIODLASTYEAR('Calendar'[Date])) | G64: #,0 | H64: Whole number | I64: Calendar | J64: Active Customers | L64: NEXORA_Measures_Core.tmdl.txt
A65: 61 | B65: 02 Time Intelligence | C65: Year over Year | D65: Customers YoY % | E65: Year-over-year growth of Customers versus the same period last year. | F65: DIVIDE([Active Customers] - [Customers LY], [Customers LY]) | G65: 0.0% | H65: Percentage | J65: Active Customers, Customers LY | K65: 0.312 | L65: NEXORA_Measures_Core.tmdl.txt
A66: 62 | B66: 02 Time Intelligence | C66: Year over Year | D66: Profit Margin LY | E66: Profit margin for the same period last year. | F66: CALCULATE([Profit Margin %], SAMEPERIODLASTYEAR('Calendar'[Date])) | G66: 0.0% | H66: Percentage | I66: Calendar | J66: Profit Margin % | L66: NEXORA_Measures_Core.tmdl.txt
A67: 63 | B67: 02 Time Intelligence | C67: Year over Year | D67: Margin Change (pts) | E67: Change in profit margin vs last year, in percentage points. | F67: IF(ISBLANK([Profit Margin LY]), BLANK(), [Profit Margin %] - [Profit Margin LY]) | G67: 0.0% | H67: Percentage | J67: Profit Margin LY, Profit Margin % | L67: NEXORA_Measures_Core.tmdl.txt
A68: 64 | B68: 03 KPI Cards | C68: Colors | D68: Net Sales Change Color | E68: Hex colour for conditional formatting of Net Sales change (green up, red down, grey when no prior period). | F68: IF(ISBLANK([Net Sales YoY %]), "#9297A2", IF([Net Sales YoY %] >= 0, "#22A861", "#E5484D")) | G68: (text) | H68: Color (hex) | J68: Net Sales YoY % | L68: NEXORA_Measures_Core.tmdl.txt
A69: 65 | B69: 03 KPI Cards | C69: Colors | D69: Profit Change Color | E69: Hex colour for conditional formatting of Profit change (green up, red down, grey when no prior period). | F69: IF(ISBLANK([Profit YoY %]), "#9297A2", IF([Profit YoY %] >= 0, "#22A861", "#E5484D")) | G69: (text) | H69: Color (hex) | J69: Profit YoY % | L69: NEXORA_Measures_Core.tmdl.txt
A70: 66 | B70: 03 KPI Cards | C70: Colors | D70: Orders Change Color | E70: Hex colour for conditional formatting of Orders change (green up, red down, grey when no prior period). | F70: IF(ISBLANK([Orders YoY %]), "#9297A2", IF([Orders YoY %] >= 0, "#22A861", "#E5484D")) | G70: (text) | H70: Color (hex) | J70: Orders YoY % | L70: NEXORA_Measures_Core.tmdl.txt
A71: 67 | B71: 03 KPI Cards | C71: Colors | D71: AOV Change Color | E71: Hex colour for conditional formatting of AOV change (green up, red down, grey when no prior period). | F71: IF(ISBLANK([AOV YoY %]), "#9297A2", IF([AOV YoY %] >= 0, "#22A861", "#E5484D")) | G71: (text) | H71: Color (hex) | J71: AOV YoY % | L71: NEXORA_Measures_Core.tmdl.txt
A72: 68 | B72: 03 KPI Cards | C72: Colors | D72: Customers Change Color | E72: Hex colour for conditional formatting of Customers change (green up, red down, grey when no prior period). | F72: IF(ISBLANK([Customers YoY %]), "#9297A2", IF([Customers YoY %] >= 0, "#22A861", "#E5484D")) | G72: (text) | H72: Color (hex) | J72: Customers YoY % | L72: NEXORA_Measures_Core.tmdl.txt
A73: 69 | B73: 03 KPI Cards | C73: Colors | D73: Margin Change Color | E73: Hex colour for conditional formatting of Margin change (green up, red down, grey when no prior period). | F73: IF(ISBLANK([Margin Change (pts)]), "#9297A2", IF([Margin Change (pts)] >= 0, "#22A861", "#E5484D")) | G73: (text) | H73: Color (hex) | J73: Margin Change (pts) | L73: NEXORA_Measures_Core.tmdl.txt
A74: 70 | B74: 03 KPI Cards | C74: Colors | D74: Cancellation Rate Color | E74: Green up to 5%, amber up to 8%, red above. | F74: IF([Cancellation Rate %] <= 0.05, "#22A861", IF([Cancellation Rate %] <= 0.08, "#F5A623", "#E5484D")) | G74: (text) | H74: Color (hex) | J74: Cancellation Rate % | L74: NEXORA_Measures_Core.tmdl.txt
A75: 71 | B75: 03 KPI Cards | C75: Colors | D75: On-Time Delivery Color | E75: Green from 90%, amber from 80%, red below. | F75: IF([On-Time Delivery %] >= 0.9, "#22A861", IF([On-Time Delivery %] >= 0.8, "#F5A623", "#E5484D")) | G75: (text) | H75: Color (hex) | J75: On-Time Delivery % | L75: NEXORA_Measures_Core.tmdl.txt
A76: 72 | B76: 03 KPI Cards | C76: Colors | D76: Return Rate Color | E76: Green up to 5%, amber up to 8%, red above. | F76: IF([Return Rate %] <= 0.05, "#22A861", IF([Return Rate %] <= 0.08, "#F5A623", "#E5484D")) | G76: (text) | H76: Color (hex) | J76: Return Rate % | L76: NEXORA_Measures_Core.tmdl.txt
A77: 73 | B77: 03 KPI Cards | C77: Labels | D77: Net Sales YoY Label | E77: Card caption such as '▲ 28.98% vs last year' for Net Sales. | F77: VAR v = [Net Sales YoY %] RETURN IF(ISBLANK(v), "No prior period", IF(v >= 0, "▲ ", "▼ ") & FORMAT(ABS(v), "0.0%") & " vs last year") | G77: (text) | H77: Text | J77: Net Sales YoY % | L77: NEXORA_Measures_Core.tmdl.txt
A78: 74 | B78: 03 KPI Cards | C78: Labels | D78: Profit YoY Label | E78: Card caption such as '▲ 28.98% vs last year' for Profit. | F78: VAR v = [Profit YoY %] RETURN IF(ISBLANK(v), "No prior period", IF(v >= 0, "▲ ", "▼ ") & FORMAT(ABS(v), "0.0%") & " vs last year") | G78: (text) | H78: Text | J78: Profit YoY % | L78: NEXORA_Measures_Core.tmdl.txt
... A82: 78 | B82: 03 KPI Cards | C82: Labels | D82: Margin Change Label | E82: Card caption such as '▲ 0.4 pts vs last year' for the profit margin. | F82: VAR v = [Margin Change (pts)] RETURN IF(ISBLANK(v), "No prior period", IF(v >= 0, "▲ ", "▼ ") & FORMAT(ABS(v) * 100, "0.0") & " pts vs last year") | G82: (text) | H82: Text | J82: Margin Change (pts) | L82: NEXORA_Measures_Core.tmdl.txt
A83: 79 | B83: 04 Products & Brands | C83: Page KPI Labels | D83: Units LY | E83: Units for the same period last year. | F83: CALCULATE([Units Sold], SAMEPERIODLASTYEAR('Calendar'[Date])) | G83: #,0 | H83: Whole number | I83: Calendar | J83: Units Sold | L83: NEXORA_Products_Page_Addon.tmdl.txt
A84: 80 | B84: 04 Products & Brands | C84: Page KPI Labels | D84: Units YoY % | E84: Year-over-year growth of Units versus the same period last year. | F84: DIVIDE([Units Sold] - [Units LY], [Units LY]) | G84: 0.0% | H84: Percentage | J84: Units Sold, Units LY | K84: 0.289 | L84: NEXORA_Products_Page_Addon.tmdl.txt
A85: 81 | B85: 04 Products & Brands | C85: Page KPI Labels | D85: Units YoY Label | E85: Card caption such as '▲ 28.98% vs last year' for Units. | F85: VAR v = [Units YoY %] RETURN IF(ISBLANK(v), "No prior period", IF(v >= 0, "▲ ", "▼ ") & FORMAT(ABS(v), "0.0%") & " vs last year") | G85: (text) | H85: Text | J85: Units YoY % | L85: NEXORA_Products_Page_Addon.tmdl.txt
A86: 82 | B86: 04 Products & Brands | C86: Page KPI Labels | D86: Units Change Color | E86: Hex colour for conditional formatting of Units change (green up, red down, grey when no prior period). | F86: IF(ISBLANK([Units YoY %]), "#9297A2", IF([Units YoY %] >= 0, "#22A861", "#E5484D")) | G86: (text) | H86: Color (hex) | J86: Units YoY % | L86: NEXORA_Products_Page_Addon.tmdl.txt
A87: 83 | B87: 04 Products & Brands | C87: Page KPI Labels | D87: Merchandise Margin LY | E87: Merchandise Margin for the same period last year. | F87: CALCULATE([Merchandise Margin %], SAMEPERIODLASTYEAR('Calendar'[Date])) | G87: 0.0% | H87: Percentage | I87: Calendar | J87: Merchandise Margin % | L87: NEXORA_Products_Page_Addon.tmdl.txt
A88: 84 | B88: 04 Products & Brands | C88: Page KPI Labels | D88: Merchandise Margin Change (pts) | E88: Change in merchandise margin vs last year, in percentage points. | F88: IF(ISBLANK([Merchandise Margin LY]), BLANK(), [Merchandise Margin %] - [Merchandise Margin LY]) | G88: 0.0% | H88: Percentage | J88: Merchandise Margin LY, Merchandise Margin % | L88: NEXORA_Products_Page_Addon.tmdl.txt
A89: 85 | B89: 04 Products & Brands | C89: Page KPI Labels | D89: Merchandise Margin Change Label | E89: Card caption such as '▲ 0.3 pts vs last year' for Merchandise Margin. | F89: VAR v = [Merchandise Margin Change (pts)] RETURN IF(ISBLANK(v), "No prior period", IF(v >= 0, "▲ ", "▼ ") & FORMAT(ABS(v) * 100, "0.0") & " pts vs last year") | G89: (text) | H89: Text | J89: Merchandise Margin Change (pts) | L89: NEXORA_Products_Page_Addon.tmdl.txt
A90: 86 | B90: 04 Products & Brands | C90: Page KPI Labels | D90: Merchandise Margin Change Color | E90: Hex colour for conditional formatting of Merchandise Margin change (green up, red down, grey when no prior period). | F90: IF(ISBLANK([Merchandise Margin Change (pts)]), "#9297A2", IF([Merchandise Margin Change (pts)] >= 0, "#22A861", "#E5484D")) | G90: (text) | H90: Color (hex) | J90: Merchandise Margin Change (pts) | L90: NEXORA_Products_Page_Addon.tmdl.txt
A91: 87 | B91: 04 Products & Brands | C91: Page KPI Labels | D91: Discount % LY | E91: Discount % for the same period last year. | F91: CALCULATE([Discount %], SAMEPERIODLASTYEAR('Calendar'[Date])) | G91: 0.0% | H91: Percentage | I91: Calendar | J91: Discount % | L91: NEXORA_Products_Page_Addon.tmdl.txt
A92: 88 | B92: 04 Products & Brands | C92: Page KPI Labels | D92: Discount Change (pts) | E92: Change in the discount rate vs last year, in percentage points. | F92: IF(ISBLANK([Discount % LY]), BLANK(), [Discount %] - [Discount % LY]) | G92: 0.0% | H92: Percentage | J92: Discount % LY, Discount % | L92: NEXORA_Products_Page_Addon.tmdl.txt
A93: 89 | B93: 04 Products & Brands | C93: Page KPI Labels | D93: Discount Change Label | E93: Card caption such as '▲ 0.3 pts vs last year' for Discount. | F93: VAR v = [Discount Change (pts)] RETURN IF(ISBLANK(v), "No prior period", IF(v >= 0, "▲ ", "▼ ") & FORMAT(ABS(v) * 100, "0.0") & " pts vs last year") | G93: (text) | H93: Text | J93: Discount Change (pts) | L93: NEXORA_Products_Page_Addon.tmdl.txt
A94: 90 | B94: 04 Products & Brands | C94: Page KPI Labels | D94: Discount Change Color | E94: Inverse logic: a lower discount rate is the good direction. | F94: IF(ISBLANK([Discount Change (pts)]), "#9297A2", IF([Discount Change (pts)] <= 0, "#22A861", "#E5484D")) | G94: (text) | H94: Color (hex) | J94: Discount Change (pts) | L94: NEXORA_Products_Page_Addon.tmdl.txt
A95: 91 | B95: 04 Products & Brands | C95: Page KPI Labels | D95: High Discount Margin Label | E95: Card caption showing the margin earned on lines discounted 30% or more. | F95: "Margin on these lines: " & FORMAT([Margin % (Discount >= 30%)], "0.0%") | G95: (text) | H95: Text | J95: Margin % (Discount >= 30%) | L95: NEXORA_Products_Page_Addon.tmdl.txt
A96: 92 | B96: 04 Products & Brands | C96: Page KPI Labels | D96: Top 10 Products Label | E96: Card caption showing the net sales of the top 10 products in $M. | F96: "Top 10 = " & FORMAT([Top 10 Products Net Sales] / 1000000, "$0.00") & "M" | G96: (text) | H96: Text | J96: Top 10 Products Net Sales | L96: NEXORA_Products_Page_Addon.tmdl.txt
A97: 93 | B97: 04 Products & Brands | C97: Page KPI Labels | D97: Unprofitable Items Label | E97: Card caption showing the size of the loss from unprofitable lines. | F97: "Loss: " & FORMAT(ABS([Loss from Unprofitable Items]), "$#,0") | G97: (text) | H97: Text | J97: Loss from Unprofitable Items | L97: NEXORA_Products_Page_Addon.tmdl.txt
A98: 94 | B98: 04 Products & Brands | C98: Performance | D98: Products Sold | E98: Number of distinct products sold in valid orders. | F98: CALCULATE( DISTINCTCOUNT(OrderItems[product_id]), Orders[order_status] <> "Cancelled", Orders[delivery_status] <> "Cancelled" ) | G98: #,0 | H98: Whole number | I98: OrderItems, Orders | L98: NEXORA_Measures_Core.tmdl.txt
A99: 95 | B99: 04 Products & Brands | C99: Performance | D99: Catalog Products | E99: Number of products in the catalogue. | F99: DISTINCTCOUNT(ProductCatalog[product_id]) | G99: #,0 | H99: Whole number | I99: ProductCatalog | L99: NEXORA_Measures_Core.tmdl.txt
A100: 96 | B100: 04 Products & Brands | C100: Performance | D100: Active Products % | E100: Share of the catalogue that sold at least once. | F100: DIVIDE([Products Sold], [Catalog Products]) | G100: 0.0% | H100: Percentage | J100: Products Sold, Catalog Products | L100: NEXORA_Measures_Core.tmdl.txt
A101: 97 | B101: 04 Products & Brands | C101: Performance | D101: Avg Product Rating | E101: Average catalogue rating of products that sold in the selection. | F101: AVERAGEX(FILTER(ProductCatalog, [Units Sold] > 0), ProductCatalog[product_rating]) | G101: 0.00 | H101: Decimal | I101: ProductCatalog | J101: Units Sold | L101: NEXORA_Measures_Core.tmdl.txt
A102: 98 | B102: 04 Products & Brands | C102: Performance Class | D102: Product Performance | E102: Classifies each product by net sales and units relative to the average product in the current selection. | F102: VAR Sales = [Net Sales] VAR Units = [Units Sold] VAR HighFactor = 1.0 VAR SolidFactor = 0.5 VAR PeerProducts = CALCULATE([Products Sold], ALLSELECTED(ProductCatalog)) VAR AvgSales = DIVIDE(CALCULATE([Net Sales], ALLSELECTED(ProductCatalog)), PeerProducts) VAR AvgUnits = DIVIDE(CALCULATE([Units Sold], ALLSELECTED(ProductCatalog)), PeerProducts) RETURN IF( NOT HASONEVALUE(ProductCatalog[product_name]) || ISBLANK(Sales), BLANK(), SWITCH( TRUE(), Sales >= AvgSales * HighFactor && Units >= AvgUnits * HighFactor, "HIGH PERFORMER", Sales >= AvgSales * SolidFactor && Units >= AvgUnits * SolidFactor, "SOLID", Sales < AvgSales * SolidFactor && Units >= AvgUnits * SolidFactor, "HIGH VOLUME / LOW VALUE", Sales >= AvgSales * SolidFactor && Units < AvgUnits * SolidFactor, "HIGH VALUE / LOW VOLUME", "LOW PERFORMER" ) ) | G102: (text) | H102: Text | I102: ProductCatalog | J102: Net Sales, Units Sold, Products Sold | L102: NEXORA_Product_Performance.tmdl.txt
A103: 99 | B103: 04 Products & Brands | C103: Performance Class | D103: Product Performance Color | E103: Colour for conditional formatting of Product Performance. | F103: SWITCH( [Product Performance], "HIGH PERFORMER", "#C8FF36", "SOLID", "#22A861", "HIGH VOLUME / LOW VALUE", "#F5A623", "HIGH VALUE / LOW VOLUME", "#4DA3FF", "LOW PERFORMER", "#E5484D", "#9297A2" ) | G103: (text) | H103: Color (hex) | J103: Product Performance | L103: NEXORA_Product_Performance.tmdl.txt
A104: 100 | B104: 04 Products & Brands | C104: Pricing | D104: Price Realization % | E104: Actual selling price vs catalogue list price (100% = sold at list). | F104: DIVIDE( [Gross Sales], CALCULATE( SUMX(OrderItems, OrderItems[quantity] * RELATED(ProductCatalog[unit_price])), Orders[order_status] <> "Cancelled", Orders[delivery_status] <> "Cancelled" ) ) | G104: 0.0% | H104: Percentage | I104: OrderItems, ProductCatalog, Orders | J104: Gross Sales | L104: NEXORA_Measures_Core.tmdl.txt
...

Sheet Model & Rules
A1: Model, Relationships and Business Rules
A2: The conventions every measure relies on.
A4: 1) Tables
A5: Table | B5: Key columns | C5: Role | D5: Rows
A6: Calendar | B6: Date, Year, Month No, Month, Quarter, Day No, Day | C6: Date table. Mark as date table; sort Month by Month No and Day by Day No. | D6: 4 years (2022-2025)
A7: Customers | B7: customer_id, customer_segment, customer_country, region, customer_acquisition_cost | C7: Customer attributes (one row per customer). | D7: 14,000
A8: Orders | B8: order_id, order_date, order_status, customer_id, delivery_status, return_status, customer_rating | C8: Order header: dates, status, delivery, returns, ratings, marketing, loyalty. | D8: 35,087
A9: OrderItems | B9: order_id, product_id, quantity, unit_price, discount_percentage, net_sales, profit | C9: Order lines: all money and quantity measures read this table. | D9: 89,105
A10: ProductCatalog | B10: product_id, product_name, product_category, product_subcategory, brand, supplier | C10: Product attributes. | D10: 1,250
A11: ALL Measures | B11: (measures only) | C11: Holds every measure. | D11: -
A13: 2) Relationships (all one-to-many, single direction)
A14: From (one side) | B14: To (many side) | C14: Purpose
A15: Calendar[Date] | B15: Orders[order_date] | C15: Time intelligence and the Year slicer.
A16: Customers[customer_id] | B16: Orders[customer_id] | C16: Customer attributes (country, segment, region).
A17: Orders[order_id] | B17: OrderItems[order_id] | C17: Links order attributes (status, channel) to order lines.
A18: ProductCatalog[product_id] | B18: OrderItems[product_id] | C18: Category, brand and product analysis.
A20: 3) Business rules
A21: Rule | B21: Definition
A22: Valid orders | B22: An order counts as a sale unless order_status or delivery_status is Cancelled. Pending and Returned orders stay in sales.
A23: Net Sales | B23: Gross sales - discount + tax + shipping (the dataset's own definition).
A24: Total Profit | B24: Net sales - product cost - shipping cost (the dataset's own definition).
A25: Profit Margin % | B25: Total profit / net sales.
A26: Merchandise Margin % | B26: (Gross sales - discount - product cost) / (gross sales - discount): product margin before tax and shipping.
A27: Money source | B27: Every money and quantity measure reads OrderItems; the Orders table supplies dates, status, delivery, returns, ratings, marketing and loyalty.
A28: Orders-level measures | B28: Delivery, returns, ratings and loyalty measures read the Orders table and are not filtered by the valid-order rule. Do not slice them by product fields.
A29: Time intelligence | B29: Calendar must be marked as a date table. Keep the Year slicer on a single year (2025) so YoY measures compare year against year.
A30: Currency | B30: All amounts are in USD (the currency column is a label).
A31: Same-column rule | B31: A measure that filters a column must not be used with that same column on a visual axis. Use KEEPFILTERS (see Reviewed Orders).
A33: 4) Calculated columns used by the visuals
A34: Column | B34: DAX | C34: Purpose | D34: Status
A35: Calendar[Year Month] | B35: FORMAT('Calendar'[Date], "MMM yyyy") | C35: Month-by-month axis; sort by Year Month No. | D35: Recommended
A36: Calendar[Year Month No] | B36: YEAR('Calendar'[Date]) * 100 + MONTH('Calendar'[Date]) | C36: Sort key for Year Month. | D36: Recommended
A37: OrderItems[Discount Band] | B37: SWITCH(TRUE(), OrderItems[discount_percentage] = 0, "0% (none)", OrderItems[discount_percentage] < 0.10, "1-9%", OrderItems[discount_percentage] < 0.20, "10-19%", OrderItems[discount_percentage] < 0.30, "20-29%", "30%+") | C37: Axis of the Discount Impact chart. | D37: Used on Products page
A38: OrderItems[Discount Band No] | B38: SWITCH(TRUE(), discount_percentage = 0, 1, < 0.10, 2, < 0.20, 3, < 0.30, 4, 5) | C38: Sort key for Discount Band. | D38: Used on Products page
A39: Customers[Acquisition Channel] | B39: Marketing channel of the customer's first order | C39: CAC and LTV by acquisition channel. | D39: Optional (advanced)
A40: Customers[Cohort Year] | B40: Year of the customer's first valid order | C40: Cohort retention matrix. | D40: Optional (advanced)
